mario/__init__.py
mario/base.py
mario/data_extractor.py
mario/dataset_builder.py
mario/dataset_specification.py
mario/dataset_splitter.py
mario/example.py
mario/excel_builder.py
mario/excel_pivot_utils.py
mario/hyper_utils.py
mario/metadata.py
mario/options.py
mario/query_builder.py
mario/utils.py
mario/validation.py
mario_pipeline_tools-0.60.dist-info/METADATA
mario_pipeline_tools-0.60.dist-info/WHEEL
mario_pipeline_tools-0.60.dist-info/top_level.txt
mario_pipeline_tools-0.60.dist-info/RECORD
